pyqa/cli/commands/config/CLI_COMMANDS_CONFIG.md
pyqa/cli/commands/config/__init__.py
pyqa/cli/commands/config/command.py
pyqa/cli/commands/config/services.py
pyqa/cli/commands/install/CLI_COMMANDS_INSTALL.md
pyqa/cli/commands/install/__init__.py
pyqa/cli/commands/install/command.py
pyqa/cli/commands/install/models.py
pyqa/cli/commands/lint/CLI_COMMANDS_LINT.md
pyqa/cli/commands/lint/__init__.py
pyqa/cli/commands/lint/cli_models.pyi
pyqa/cli/commands/lint/command.py
pyqa/cli/commands/lint/explain.py
pyqa/cli/commands/lint/fetch.py
pyqa/cli/commands/lint/literals.py
pyqa/cli/commands/lint/meta.py
pyqa/cli/commands/lint/params.py
pyqa/cli/commands/lint/preparation.py
pyqa/cli/commands/lint/progress.py
pyqa/cli/commands/lint/reporting.py
pyqa/cli/commands/lint/runtime.py
pyqa/cli/commands/lint/cli_models/CLI_COMMANDS_LINT_CLI_MODELS.md
pyqa/cli/commands/lint/cli_models/__init__.py
pyqa/cli/commands/lint/cli_models/assembly.py
pyqa/cli/commands/lint/cli_models/coercion.py
pyqa/cli/commands/lint/cli_models/constants.py
pyqa/cli/commands/lint/cli_models/meta.py
pyqa/cli/commands/lint/cli_models/models.py
pyqa/cli/commands/lint/cli_models/output.py
pyqa/cli/commands/lint/cli_models/overrides.py
pyqa/cli/commands/lint/cli_models/runtime.py
pyqa/cli/commands/lint/cli_models/selection.py
pyqa/cli/commands/lint/cli_models/severity.py
pyqa/cli/commands/lint/cli_models/targets.py
pyqa/config/CONFIG.md
pyqa/config/__init__.py
pyqa/config/types.py
pyqa/config/types.pyi
pyqa/config/utils.py
pyqa/config/defaults/CONFIG_DEFAULTS.md
pyqa/config/defaults/__init__.py
pyqa/config/loaders/CONFIG_LOADERS.md
pyqa/config/loaders/__init__.py
pyqa/config/loaders/sources.py
pyqa/config/model_defs/CONFIG_MODEL_DEFS.md
pyqa/config/model_defs/__init__.py
pyqa/config/model_defs/base.py
pyqa/config/model_defs/config_container.py
pyqa/config/model_defs/enums.py
pyqa/config/model_defs/sentinels.py
pyqa/config/model_defs/value_types.py
pyqa/config/models/CONFIG_MODELS.md
pyqa/config/models/__init__.py
pyqa_lint-0.3.0.dist-info/METADATA
pyqa_lint-0.3.0.dist-info/WHEEL
pyqa_lint-0.3.0.dist-info/entry_points.txt
pyqa_lint-0.3.0.dist-info/licenses/LICENSE
pyqa_lint-0.3.0.dist-info/RECORD
