Metadata-Version: 2.4
Name: pyqa_lint
Version: 0.3.0
Summary: Polyglot lint orchestration toolkit
License: Copyright (c) 2025 Blackcat Informatics® Inc.
License-File: LICENSE
Requires-Python: >=3.13
Requires-Dist: autopep8>=2.3.2
Requires-Dist: bandit[baseline,sarif,toml]>=1.8.6
Requires-Dist: black>=25.9.0
Requires-Dist: botocore-stubs>=1.40.32
Requires-Dist: bs4>=0.0.2
Requires-Dist: cython>=3.1.4
Requires-Dist: isort>=6.0.1
Requires-Dist: jsonschema>=4.23.0
Requires-Dist: markdown>=3.9
Requires-Dist: mdformat-footnote>=0.1.1
Requires-Dist: mdformat-frontmatter>=2.0.8
Requires-Dist: mdformat-gfm-alerts>=2.0.0
Requires-Dist: mdformat-gfm>=0.4.1
Requires-Dist: mdformat-myst>=0.2.2
Requires-Dist: mdformat>=0.7.22
Requires-Dist: mypy-extensions>=1.1.0
Requires-Dist: mypy>=1.18.2
Requires-Dist: packaging>=24.1
Requires-Dist: pip>=25.3
Requires-Dist: pycodestyle>=2.14.0
Requires-Dist: pydantic>=2.9.2
Requires-Dist: pyflakes>=3.4.0
Requires-Dist: pylint-htmf>=0.1.1
Requires-Dist: pylint-plugin-utils>=0.9.0
Requires-Dist: pylint-pydantic>=0.3.5
Requires-Dist: pylint-pytest>=1.1.7
Requires-Dist: pylint-sqlalchemy>=0.3.0
Requires-Dist: pylint-venv>=3.0.4
Requires-Dist: pylint>=3.3.8
Requires-Dist: pyright>=1.1.405
Requires-Dist: pytest-bdd>=8.1.0
Requires-Dist: pytest>=8.2.0
Requires-Dist: pyupgrade>=3.20.0
Requires-Dist: ruff>=0.13.2
Requires-Dist: spacy>=3.8.7
Requires-Dist: sqlalchemy-stubs>=0.4
Requires-Dist: sqlfluff>=3.4.2
Requires-Dist: tree-sitter-bash
Requires-Dist: tree-sitter-dockerfile
Requires-Dist: tree-sitter-go>=0.25.0
Requires-Dist: tree-sitter-javascript>=0.25.0
Requires-Dist: tree-sitter-json>=0.24.8
Requires-Dist: tree-sitter-lua
Requires-Dist: tree-sitter-make
Requires-Dist: tree-sitter-markdown>=0.5.1
Requires-Dist: tree-sitter-php
Requires-Dist: tree-sitter-python>=0.25.0
Requires-Dist: tree-sitter-rust>=0.24.0
Requires-Dist: tree-sitter-sql>=0.3.8
Requires-Dist: tree-sitter-toml
Requires-Dist: tree-sitter-typescript>=0.21.0
Requires-Dist: tree-sitter-yaml
Requires-Dist: tree-sitter>=0.25.1
Requires-Dist: twine>=6.2.0
Requires-Dist: typer>=0.12
Requires-Dist: types-aiofiles>=24.1.0.20250822
Requires-Dist: types-cffi>=1.17.0.20250915
Requires-Dist: types-click>=7.1.8
Requires-Dist: types-colorama>=0.4.15.20250801
Requires-Dist: types-decorator>=5.2.0.20250324
Requires-Dist: types-docutils>=0.22.2.20250924
Requires-Dist: types-html5lib>=1.1.11.20250917
Requires-Dist: types-jinja2>=2.11.9
Requires-Dist: types-jsonschema>=4.25.1.20250822
Requires-Dist: types-markdown>=3.9.0.20250906
Requires-Dist: types-pexpect>=4.9.0.20250916
Requires-Dist: types-pygments>=2.19.0.20250809
Requires-Dist: types-pyyaml>=6.0.12.20250915
Requires-Dist: types-regex>=2025.9.1.20250903
Requires-Dist: types-requests>=2.32.4.20250913
Requires-Dist: types-setuptools>=80.9.0.20250822
Requires-Dist: types-tqdm>=4.67.0.20250809
Requires-Dist: typing-extensions>=4.15.0
Requires-Dist: typing-inspection>=0.4.1
Requires-Dist: uv>=0.8.22
Requires-Dist: vulture>=2.14
Requires-Dist: yamllint>=1.37.1
Provides-Extra: dev
